useb/__init__.py
useb/downloading.py
useb/evaluating.py
useb/evaluators/__init__.py
useb/evaluators/askubuntu.py
useb/evaluators/base.py
useb/evaluators/cqadupstack.py
useb/evaluators/scidocs.py
useb/evaluators/twitterpara.py
useb/examples/__init__.py
useb/examples/eval_sbert_all.py
useb/examples/eval_sbert_askubuntu.py
useb-0.0.1.dist-info/LICENSE
useb-0.0.1.dist-info/METADATA
useb-0.0.1.dist-info/WHEEL
useb-0.0.1.dist-info/top_level.txt
useb-0.0.1.dist-info/RECORD
