Metadata-Version: 2.1
Name: useb
Version: 0.0.1
Summary: Heterogenous, Task- and Domain-Specific Benchmark for Unsupervised Sentence Embeddings used in the TSDAE paper.
Home-page: https://github.com/kwang2049/useb
Author: Kexin Wang
Author-email: kexin.wang.2049@gmail.com
License: UNKNOWN
Platform: UNKNOWN
Classifier: Programming Language :: Python :: 3
Classifier: License :: OSI Approved :: Apache Software License
Classifier: Operating System :: OS Independent
Requires-Python: >=3.6
License-File: LICENSE
Requires-Dist: sentence-transformers (>=1.2.0)
Requires-Dist: pytrec-eval
